semla/__init__.py
semla/cli.py
semla/reports.py
semla/semla.py
semla/visualizations.py
semla-0.1.0.dist-info/DESCRIPTION.rst
semla-0.1.0.dist-info/METADATA
semla-0.1.0.dist-info/RECORD
semla-0.1.0.dist-info/WHEEL
semla-0.1.0.dist-info/entry_points.txt
semla-0.1.0.dist-info/metadata.json
semla-0.1.0.dist-info/top_level.txt
