Metadata-Version: 2.0
Name: semla
Version: 0.1.0
Summary: Study, ExaMine, Learn and Analyze
Home-page: https://github.com/eyadsibai/semla
Author: Eyad Sibai
Author-email: eyad.alsibai@gmail.com
License: MIT license
Keywords: semla
Platform: UNKNOWN
Classifier: Development Status :: 2 - Pre-Alpha
Classifier: Intended Audience :: Developers
Classifier: License :: OSI Approved :: MIT License
Classifier: Natural Language :: English
Classifier: Programming Language :: Python :: 3
Classifier: Programming Language :: Python :: 3.5
Classifier: Programming Language :: Python :: 3.6
Requires-Dist: Click (>=6.0)
Requires-Dist: matplotlib
Requires-Dist: numpy
Requires-Dist: pandas
Requires-Dist: pandas-profiling
Requires-Dist: seaborn
